ethbind/__init__.py
ethbind/base.py
ethbind/types.py
ethbind-0.0.1.dist-info/LICENSE
ethbind-0.0.1.dist-info/METADATA
ethbind-0.0.1.dist-info/WHEEL
ethbind-0.0.1.dist-info/RECORD
