Metadata-Version: 2.1
Name: ethbind
Version: 0.0.1
Summary: P4A Kivy/KivyMD Developer sample & tools.
License: Apache 2.0
Keywords: etherium,eth,code-gen,bind,translation,dev,ipfs,docs,tester
Author: BlackCatDevel0per
Author-email: bcdev@mail.ru
Requires-Python: >=3.8.1,<4.0
Classifier: Development Status :: 5 - Production/Stable
Classifier: Environment :: Console
Classifier: Intended Audience :: Developers
Classifier: Intended Audience :: System Administrators
Classifier: License :: OSI Approved :: Apache Software License
Classifier: License :: Other/Proprietary License
Classifier: Programming Language :: Python :: 3
Classifier: Programming Language :: Python :: 3.9
Classifier: Programming Language :: Python :: 3.10
Classifier: Programming Language :: Python :: 3.11
Classifier: Programming Language :: Python :: 3.12
Classifier: Programming Language :: Python :: 3.8
Classifier: Programming Language :: Python :: Implementation :: PyPy
Classifier: Topic :: Software Development :: Libraries :: Python Modules
Classifier: Typing :: Typed
Requires-Dist: web3 (>=6.20.0,<7.0.0)
Project-URL: Documentation, https://github.com/BlackCatDevel0per/ethbind
Project-URL: Homepage, https://github.com/BlackCatDevel0per/ethbind
Project-URL: Repository, https://github.com/BlackCatDevel0per/ethbind
